data_connectors/__init__.py
data_connectors/reader.py
data_connectors/writer.py
data_connectors_qna-0.0.0.dist-info/METADATA
data_connectors_qna-0.0.0.dist-info/WHEEL
data_connectors_qna-0.0.0.dist-info/top_level.txt
data_connectors_qna-0.0.0.dist-info/RECORD
